atprotocol/__init__.py
atprotocol/agent.py
atprotocol/bsky/__init__.py
atprotocol/bsky/agent.py
atprotocol/bsky/types.py
atprotocol/types.py
atprotocol-0.0.2.dist-info/LICENSE
atprotocol-0.0.2.dist-info/WHEEL
atprotocol-0.0.2.dist-info/METADATA
atprotocol-0.0.2.dist-info/RECORD
